{
  "a": [
    "astrazeneca",
    "protection",
    "study",
    "omicron",
    "pfizer",
    "accused",
    "health",
    "lethal",
    "fake",
    "protect"
  ],
  "r": [
    "employees",
    "mandate",
    "military",
    "nationwide",
    "contractors",
    "federal",
    "judge",
    "required",
    "requirement",
    "mandatory"
  ],
  "c": [
    "transparency",
    "data",
    "pfizer",
    "passports",
    "clean",
    "act",
    "fda",
    "coming",
    "unless",
    "countries"
  ],
  "p": [
    "political",
    "biden",
    "trump",
    "republican",
    "support",
    "wearing",
    "workers",
    "administration",
    "ppl",
    "mandate"
  ],
  "e": [
    "booster",
    "arm",
    "dose",
    "double",
    "pfizer",
    "moderna",
    "home",
    "lost",
    "heart",
    "life"
  ],
  "o": [
    "anti",
    "astrazeneca",
    "friend",
    "sick",
    "don",
    "mask",
    "effective",
    "lecture",
    "love",
    "mother"
  ],
  "nc": [
    "flu",
    "truth",
    "virus",
    "pandemic",
    "news",
    "vaccination",
    "vaccine",
    "covid",
    "vax"
  ]
}
